ucumos/__init__.py
ucumos/logging.py
ucumos/metadata.py
ucumos/modeling.py
ucumos/pickler.py
ucumos/protogen.py
ucumos/session.py
ucumos/utils.py
ucumos/wrapped.py
ucumos-0.8.4.dist-info/LICENSE
ucumos-0.8.4.dist-info/METADATA
ucumos-0.8.4.dist-info/WHEEL
ucumos-0.8.4.dist-info/top_level.txt
ucumos-0.8.4.dist-info/RECORD
